hopcroftkarp/__init__.py
hopcroftkarp-1.2.4.dist-info/zip-safe
hopcroftkarp-1.2.4.dist-info/DESCRIPTION.rst
hopcroftkarp-1.2.4.dist-info/RECORD
hopcroftkarp-1.2.4.dist-info/top_level.txt
hopcroftkarp-1.2.4.dist-info/metadata.json
hopcroftkarp-1.2.4.dist-info/WHEEL
hopcroftkarp-1.2.4.dist-info/METADATA
test/__init__.py
test/test_hopcroftkarp.py
