Metadata-Version: 2.0
Name: hopcroftkarp
Version: 1.2.4
Summary: Implementation of HopcroftKarp's algorithm
Home-page: https://github.com/sofiat-olaosebikan/hopcroftkarp
Author: Sofiat Olaosebikan
Author-email: sofiat@aims.edu.gh
License: GPL
Keywords: hopcroftkarp algorithm,maximum cardinality matching,bipartite graphs
Platform: UNKNOWN
Classifier: Development Status :: 3 - Alpha
Classifier: Intended Audience :: Science/Research
Classifier: License :: OSI Approved :: GNU General Public License v3 (GPLv3)
Classifier: Programming Language :: Python :: 2.6
Classifier: Programming Language :: Python :: 2.7
Classifier: Programming Language :: Python :: 3.2
Classifier: Programming Language :: Python :: 3.3
Classifier: Programming Language :: Python :: 3.4
